mantis_baseboxes_helpers/__init__.py
mantis_baseboxes_helpers/baseboxes_helpers.py
mantis_common_model/__init__.py
mantis_common_model/cpe.py
mantis_common_model/ioc_model.py
mantis_common_model/pagination.py
mantis_dataset_model/.gitignore
mantis_dataset_model/__init__.py
mantis_dataset_model/asset_report_model.py
mantis_dataset_model/dataset_analysis_model.py
mantis_dataset_model/dataset_model.py
mantis_redteam_model/__init__.py
mantis_redteam_model/atomic_model.py
mantis_redteam_model/infrastructure.py
mantis_redteam_model/report_model.py
mantis_redteam_model/topic_model.py
mantis_redteam_model/unit_attack_model.py
mantis_scenario_model/__init__.py
mantis_scenario_model/api_scenario_model.py
mantis_scenario_model/basebox_model.py
mantis_scenario_model/common.py
mantis_scenario_model/lab_config_model.py
mantis_scenario_model/lab_model.py
mantis_scenario_model/link.py
mantis_scenario_model/log_collector_model.py
mantis_scenario_model/mitre/attck_to_nist_controls.json
mantis_scenario_model/mitre/generate_mitre_json.py
mantis_scenario_model/mitre/merged_enterprise_attck_v2.json
mantis_scenario_model/mitre/merged_ics_attck_v2.json
mantis_scenario_model/mitre/merged_mobile_attck_v2.json
mantis_scenario_model/mitre/merged_nist_controls_v1.json
mantis_scenario_model/mitre/merged_pre_attck_v1.json
mantis_scenario_model/mitre/mitre.json
mantis_scenario_model/node.py
mantis_scenario_model/notification_model.py
mantis_scenario_model/scenario_model.py
mantis_scenario_model/signature_model.py
mantis_scenario_model/stats_model.py
mantis_scenario_model/topology_model.py
mantis_scenario_model/unit_attack_model.py
mantis_models-3.4.0.dist-info/METADATA
mantis_models-3.4.0.dist-info/WHEEL
mantis_models-3.4.0.dist-info/RECORD
