Metadata-Version: 2.1
Name: mantis-models
Version: 3.4.0
Summary: M&NTIS library containing models used in M&NTIS components
License: MIT
Author: AMOSSYS
Requires-Python: >=3.8.1,<4.0.0
Classifier: License :: OSI Approved :: MIT License
Classifier: Programming Language :: Python :: 3
Classifier: Programming Language :: Python :: 3.9
Classifier: Programming Language :: Python :: 3.10
Classifier: Programming Language :: Python :: 3.11
Classifier: Programming Language :: Python :: 3.12
Classifier: Programming Language :: Python :: 3.13
Requires-Dist: packaging (>=14.1)
Requires-Dist: pydantic (>=2.10.3,<3.0.0)
Requires-Dist: pyyaml (>=6.0.1,<7.0.0)
Requires-Dist: ruamel.yaml (>=0.16.10,<0.17.0)
